codigo/__init__.py
codigo/code.py
calcmaster-0.0.1.dist-info/METADATA
calcmaster-0.0.1.dist-info/WHEEL
calcmaster-0.0.1.dist-info/top_level.txt
calcmaster-0.0.1.dist-info/RECORD
