Metadata-Version: 2.1
Name: calcmaster
Version: 0.0.1
Summary: paquete calculadora basica master 
Home-page: https://github.com/juliorodriguez23/proyectos
Author: juliorodriguez
Author-email: julio_rz23@hotmail.com
License: UNKNOWN
Platform: UNKNOWN
